setup.py
doc/python-message-0.1.0-slide-gadget.xml
message/__init__.py
message/message.py
message/observable.py
message.egg-info/PKG-INFO
message.egg-info/SOURCES.txt
message.egg-info/dependency_links.txt
message.egg-info/top_level.txt
test/testobservable.py