Metadata-Version: 1.0
Name: message
Version: 0.2.0
Summary: A message-oriented programming library for python.
Home-page: http://code.google.com/p/python-message/
Author: LaiYonghao
Author-email: mail@laiyonghao.com
License: MIT
Keywords: message-oriented,signal-slot,publish-subscribe
Platform: Independant
Classifier: Development Status :: 3 - Alpha
Classifier: License :: OSI Approved :: MIT License
Classifier: Operating System :: OS Independent
Classifier: Programming Language :: Python
Classifier: Topic :: Software Development
Classifier: Topic :: Software Development :: Libraries
Classifier: Topic :: Software Development :: Libraries :: Python Modules
Classifier: Topic :: Utilities
